photon/__init__.py
photon/photon.py
photon/user_agents_db.py
photon-1.1.3.1.dist-info/METADATA
photon-1.1.3.1.dist-info/RECORD
photon-1.1.3.1.dist-info/WHEEL
photon-1.1.3.1.dist-info/top_level.txt
