Metadata-Version: 2.1
Name: photon
Version: 1.1.3.1
Summary: Incredibly fast crawler designed for OSINT
Home-page: https://github.com/s0md3v/Photon
Author: Somdev Sangwan
Author-email: s0md3v@gmail.com
License: MIT
Keywords: photon,crawling,python crawling
Platform: UNKNOWN
Classifier: License :: OSI Approved :: MIT License
Classifier: Intended Audience :: Developers
Classifier: Development Status :: 5 - Production/Stable
Classifier: Programming Language :: Python
Classifier: Programming Language :: Python :: 2
Classifier: Programming Language :: Python :: 2.6
Classifier: Programming Language :: Python :: 2.7
Classifier: Programming Language :: Python :: 3
Classifier: Programming Language :: Python :: 3.4
Classifier: Programming Language :: Python :: 3.5
Classifier: Programming Language :: Python :: 3.6
Classifier: Operating System :: OS Independent
Classifier: Environment :: Console
Classifier: Topic :: Software Development :: Libraries :: Python Modules
Requires-Dist: requests
Requires-Dist: urllib3
